README.md
setup.py
pyrplidar/__init__.py
pyrplidar/pyrplidar.py
pyrplidar/pyrplidar_protocol.py
pyrplidar/pyrplidar_serial.py
pyrplidar.egg-info/PKG-INFO
pyrplidar.egg-info/SOURCES.txt
pyrplidar.egg-info/dependency_links.txt
pyrplidar.egg-info/requires.txt
pyrplidar.egg-info/top_level.txt
test/test_pyrplidar_protocol.py