Metadata-Version: 2.1
Name: pyrplidar
Version: 0.1.0
Summary: Full-featured python library for Slamtec RPLIDAR series
Home-page: https://github.com/Hyun-je/pyrplidar
Author: Hyun-je
Author-email: bigae2@gmail.com
License: MIT
Platform: Cross Platform
Classifier: Programming Language :: Python :: 3
Classifier: License :: OSI Approved :: MIT License
Classifier: Operating System :: OS Independent
